tabella/__init__.py
tabella/_app.py
tabella/_cache.py
tabella/_common.py
tabella/_monitor.py
tabella/_routes.py
tabella/_templating_engine.py
tabella/_util.py
tabella/py.typed
tabella/static/android-icon-144x144.png
tabella/static/android-icon-192x192.png
tabella/static/android-icon-36x36.png
tabella/static/android-icon-48x48.png
tabella/static/android-icon-72x72.png
tabella/static/android-icon-96x96.png
tabella/static/apple-icon-114x114.png
tabella/static/apple-icon-120x120.png
tabella/static/apple-icon-144x144.png
tabella/static/apple-icon-152x152.png
tabella/static/apple-icon-180x180.png
tabella/static/apple-icon-57x57.png
tabella/static/apple-icon-60x60.png
tabella/static/apple-icon-72x72.png
tabella/static/apple-icon-76x76.png
tabella/static/apple-icon-precomposed.png
tabella/static/apple-icon.png
tabella/static/browserconfig.xml
tabella/static/favicon-16x16.png
tabella/static/favicon-32x32.png
tabella/static/favicon-96x96.png
tabella/static/favicon.ico
tabella/static/highlight.min.js
tabella/static/htmx.js
tabella/static/manifest.json
tabella/static/ms-icon-144x144.png
tabella/static/ms-icon-150x150.png
tabella/static/ms-icon-310x310.png
tabella/static/ms-icon-70x70.png
tabella/static/out/clients/python/tabella-integration-test-ws-client/README.md
tabella/static/out/clients/python/tabella-integration-test-ws-client/setup.py
tabella/static/out/clients/python/tabella-integration-test-ws-client/tabella_integration_test_ws_client/__init__.py
tabella/static/out/clients/python/tabella-integration-test-ws-client/tabella_integration_test_ws_client/client.py
tabella/static/out/clients/python/tabella-integration-test-ws-client/tabella_integration_test_ws_client/models.py
tabella/static/out/clients/python/tabella-integration-test-ws-client-1.1.1-py.zip
tabella/static/output.css
tabella/static/tabella.js
tabella/static/vs.min.css
tabella/static/vs2015.min.css
tabella/templates/error.html
tabella/templates/index.html
tabella/templates/json.html
tabella-2.4.1.dist-info/WHEEL
tabella-2.4.1.dist-info/entry_points.txt
tabella-2.4.1.dist-info/METADATA
tabella-2.4.1.dist-info/RECORD
