Metadata-Version: 2.4
Name: tabella
Version: 2.4.1
Summary: Open-RPC API hosting and interactive documentation.
Author: Matthew Burkard
Author-email: Matthew Burkard <matthewjburkard@gmail.com>
License-Expression: Apache-2.0
Classifier: Intended Audience :: Developers
Classifier: License :: OSI Approved :: Apache Software License
Classifier: Programming Language :: Python :: 3.10
Classifier: Programming Language :: Python :: 3.11
Classifier: Topic :: Software Development
Classifier: Topic :: Software Development :: Libraries
Classifier: Topic :: Software Development :: Libraries :: Python Modules
Classifier: Typing :: Typed
Requires-Dist: case-switcher>=1.3.13
Requires-Dist: httpx>=0.28.1
Requires-Dist: jinja2>=3.1.6
Requires-Dist: lorem-pysum>=1.4.11
Requires-Dist: openrpc>=10.5.0
Requires-Dist: openrpcclientgenerator>=0.49.0
Requires-Dist: pydantic>=2.11.9
Requires-Dist: starlette>=0.48.0
Requires-Dist: uvicorn>=0.37.0
Requires-Python: >=3.10
Project-URL: homepage, https://gitlab.com/mburkard/tabella
Project-URL: repository, https://gitlab.com/mburkard/tabella
